{
  "runtimeOptions": {
    "tfm": "net8.0",
    "frameworks": [
      {
        "name": "Microsoft.NETCore.App",
        "version": "8.0.0"
      },
      {
        "name": "Microsoft.WindowsDesktop.App",
        "version": "8.0.0"
      }
    ],
    "additionalProbingPaths": [
      "D:\\Users\\Administrator\\.dotnet\\store\\|arch|\\|tfm|",
      "D:\\Users\\Administrator\\.nuget\\packages",
      "D:\\Program Files (x86)\\Microsoft Visual Studio\\Shared\\NuGetPackages"
    ],
    "configProperties": {
      "System.Reflection.Metadata.MetadataUpdater.IsSupported": false,
      "System.Runtime.Serialization.EnableUnsafeBinaryFormatterSerialization": true,
      "Microsoft.NETCore.DotNetHostPolicy.SetAppPaths": true
    }
  }
}